ioframe/__init__.py
ioframe/_suffix.py
ioframe/core/__init__.py
ioframe/core/backend.py
ioframe/core/registry.py
ioframe/core/types.py
ioframe/io/__init__.py
ioframe/io/_base.py
ioframe/io/reader.py
ioframe/io/writer.py
ioframe/mixin/__init__.py
ioframe/mixin/compression.py
ioframe/mixin/engine/__init__.py
ioframe/mixin/engine/fastparquet.py
ioframe/mixin/engine/pandas.py
ioframe/mixin/engine/pyarrow.py
ioframe/mixin/engine/pyroot.py
ioframe/mixin/engine/pytables.py
ioframe/mixin/engine/uproot.py
ioframe/mixin/kind/__init__.py
ioframe/mixin/kind/csv.py
ioframe/mixin/kind/feather.py
ioframe/mixin/kind/hdf5.py
ioframe/mixin/kind/parquet.py
ioframe/mixin/kind/root.py
ioframe/mixin/kind_engine/__init__.py
ioframe/mixin/kind_engine/csv_pandas.py
ioframe/mixin/kind_engine/csv_pyarrow.py
ioframe/perf/__init__.py
ioframe/perf/_measure.py
ioframe/perf/config/__init__.py
ioframe/perf/config/_argument.py
ioframe/perf/config/_io.py
ioframe/perf/config/_loop.py
ioframe/perf/config/_result.py
ioframe/perf/config/_stats.py
ioframe/perf/metric/__init__.py
ioframe/perf/metric/_base.py
ioframe/perf/metric/_io.py
ioframe/perf/metric/_size.py
ioframe/perf/metric/_time.py
ioframe/py.typed
ioframe/reader/__init__.py
ioframe/reader/csv_pandas.py
ioframe/reader/csv_pyarrow.py
ioframe/reader/feather.py
ioframe/reader/hdf5.py
ioframe/reader/parquet.py
ioframe/reader/root_pyroot.py
ioframe/reader/root_uproot.py
ioframe/tool/__init__.py
ioframe/tool/pyroot.py
ioframe/writer/__init__.py
ioframe/writer/csv_pandas.py
ioframe/writer/csv_pyarrow.py
ioframe/writer/feather.py
ioframe/writer/hdf5.py
ioframe/writer/parquet.py
ioframe/writer/root_pyroot.py
ioframe/writer/root_uproot.py
ioframe-0.1.2.dist-info/WHEEL
ioframe-0.1.2.dist-info/METADATA
ioframe-0.1.2.dist-info/RECORD
