Metadata-Version: 2.3
Name: ioframe
Version: 0.1.2
Summary: Unified API for reading and writing Pandas DataFrames across multiple file formats and engines.
Keywords: pandas,dataframe,io,root,cern
Author: anthonyc
Author-email: anthonyc <anthony.correia@cern.ch>
License: Apache License (2.0)
Classifier: Development Status :: 4 - Beta
Classifier: Intended Audience :: Science/Research
Classifier: License :: OSI Approved :: Apache Software License
Classifier: Operating System :: OS Independent
Classifier: Programming Language :: Python :: 3
Classifier: Programming Language :: Python :: 3 :: Only
Classifier: Programming Language :: Python :: 3.11
Classifier: Programming Language :: Python :: 3.12
Classifier: Programming Language :: Python :: 3.13
Classifier: Topic :: Scientific/Engineering
Requires-Dist: pandas>=2.3.1
Requires-Dist: pydantic>=2.11.7
Requires-Dist: fastparquet>=2024.11.0 ; extra == 'fastparquet'
Requires-Dist: tables>=3.10.2 ; extra == 'hdf5'
Requires-Dist: pyarrow>=21.0.0 ; extra == 'pyarrow'
Requires-Dist: awkward-pandas>=2023.8.0 ; extra == 'uproot'
Requires-Dist: uproot>=5.6.4 ; extra == 'uproot'
Requires-Dist: zstandard>=0.23.0 ; extra == 'zstd'
Requires-Python: >=3.11
Project-URL: Changelog, https://gitlab.cern.ch/particlepredatorinvasion/ioframe/-/releases
Project-URL: Documentation, https://ioframe.docs.cern.ch
Project-URL: Homepage, https://gitlab.cern.ch/particlepredatorinvasion/ioframe
Project-URL: Issues, https://gitlab.cern.ch/particlepredatorinvasion/ioframe/issues
Project-URL: Repository, https://gitlab.cern.ch/particlepredatorinvasion/ioframe
Provides-Extra: fastparquet
Provides-Extra: hdf5
Provides-Extra: pyarrow
Provides-Extra: uproot
Provides-Extra: zstd
